btc_sentiment_analysis/__init__.py
btc_sentiment_analysis/analyzers.py
btc_sentiment_analysis/article.py
btc_sentiment_analysis/crawler.py
btc_sentiment_analysis/visualizer.py
btc_sentiment_analysis-0.0.2.dist-info/LICENSE.txt.txt
btc_sentiment_analysis-0.0.2.dist-info/METADATA
btc_sentiment_analysis-0.0.2.dist-info/WHEEL
btc_sentiment_analysis-0.0.2.dist-info/top_level.txt
btc_sentiment_analysis-0.0.2.dist-info/RECORD
