Metadata-Version: 2.1
Name: btc-sentiment-analysis
Version: 0.0.2
Summary: A small sentiment analysis library for bitcoin
Home-page: https://github.com/diegofigueroa79/btc-sentiment-analysis
Author-email: diegofigueroa79@gmail.com
License: UNKNOWN
Platform: UNKNOWN
Classifier: Programming Language :: Python :: 3
Classifier: License :: OSI Approved :: MIT License
Classifier: Operating System :: OS Independent
Requires-Python: >=3.6
Requires-Dist: beautifulsoup4
Requires-Dist: lxml
Requires-Dist: matplotlib
Requires-Dist: newspaper3k
Requires-Dist: nltk
Requires-Dist: pandas
Requires-Dist: requests
Requires-Dist: seaborn
Requires-Dist: textblob
Provides-Extra: dev
Requires-Dist: pytest ; extra == 'dev'
